mcp_server_neo4j/__init__.py
mcp_server_neo4j/__main__.py
mcp_server_neo4j/server.py
mcp_server_neo4j-0.1.8.dist-info/METADATA
mcp_server_neo4j-0.1.8.dist-info/WHEEL
mcp_server_neo4j-0.1.8.dist-info/entry_points.txt
mcp_server_neo4j-0.1.8.dist-info/RECORD
