Metadata-Version: 2.4
Name: mcp-server-neo4j
Version: 0.1.8
Summary: 一个提供Neo4j数据库操作功能的Model Context Protocol服务器
Author: MCP Team
License: MIT
Keywords: database,graph,llm,mcp,neo4j
Classifier: Development Status :: 4 - Beta
Classifier: Intended Audience :: Developers
Classifier: License :: OSI Approved :: MIT License
Classifier: Programming Language :: Python :: 3
Classifier: Programming Language :: Python :: 3.10
Requires-Python: >=3.10
Requires-Dist: mcp>=1.0.0
Requires-Dist: neo4j>=5.0.0
Requires-Dist: pydantic>=2.0.0
